aiot_bootrom/__init__.py
aiot_bootrom/bootrom.py
aiot_bootrom/bin/bootrom-tool
aiot_bootrom/bin/aarch64/linux/bootrom-tool
aiot_bootrom/bin/amd64/linux/bootrom-tool
aiot_bootrom/bin/amd64/windows/bootrom-tool.exe
aiot_bootrom/bin/x86_64/linux/bootrom-tool
genio_bootrom-1.2.1.dist-info/licenses/LICENSE
genio_bootrom-1.2.1.dist-info/METADATA
genio_bootrom-1.2.1.dist-info/WHEEL
genio_bootrom-1.2.1.dist-info/entry_points.txt
genio_bootrom-1.2.1.dist-info/top_level.txt
genio_bootrom-1.2.1.dist-info/RECORD
