Metadata-Version: 2.4
Name: genio-bootrom
Version: 1.2.1
Summary: Tool to bootstrap the flashing on MediaTek Genio SoCs
Home-page: https://gitlab.com/mediatek/aiot/bsp/genio-bootrom
Author: Fabien Parent
Maintainer: Pablo Sun
Maintainer-email: pablo.sun@mediatek.com
Classifier: Programming Language :: Python :: 3
Classifier: License :: Other/Proprietary License
Classifier: Operating System :: POSIX :: Linux
Classifier: Operating System :: Microsoft :: Windows
Classifier: Topic :: Software Development :: Embedded Systems
License-File: LICENSE
Dynamic: author
Dynamic: classifier
Dynamic: home-page
Dynamic: license-file
Dynamic: maintainer
Dynamic: maintainer-email
Dynamic: summary
